primosalonzo1.py
primosalonzo1-0.0.1.dist-info/LICENSE.txt
primosalonzo1-0.0.1.dist-info/METADATA
primosalonzo1-0.0.1.dist-info/WHEEL
primosalonzo1-0.0.1.dist-info/top_level.txt
primosalonzo1-0.0.1.dist-info/RECORD
