Metadata-Version: 2.1
Name: primosalonzo1
Version: 0.0.1
Summary: Enlista todos los primos desde 1 hasta un numero n
Home-page: https://github.com/GermanAlonzo/ModuloPrimosAlonzo1
Author: German Alonzo
License: UNKNOWN
Platform: UNKNOWN
Classifier: Programming Language :: Python :: 3
Classifier: Programming Language :: Python :: 3.6
Classifier: Programming Language :: Python :: 3.7
Classifier: License :: OSI Approved :: GNU General Public License v2 or later (GPLv2+)
Classifier: Operating System :: OS Independent
